telegram_mcp/__init__.py
telegram_mcp/cache.py
telegram_mcp/cli.py
telegram_mcp/config.py
telegram_mcp/server.py
telegram_reader_mcp-0.3.5.dist-info/METADATA
telegram_reader_mcp-0.3.5.dist-info/WHEEL
telegram_reader_mcp-0.3.5.dist-info/entry_points.txt
telegram_reader_mcp-0.3.5.dist-info/RECORD
