Metadata-Version: 2.4
Name: telegram-reader-mcp
Version: 0.3.5
Summary: Telegram MCP Server - 让 Claude 读取 Telegram 消息
Requires-Python: >=3.11
Requires-Dist: aiosqlite>=0.19.0
Requires-Dist: mcp>=1.0.0
Requires-Dist: python-dotenv>=1.0.0
Requires-Dist: telethon>=1.34.0
